colight_cli.py
colight_prose/README.md
colight_prose/__init__.py
colight_prose/api.py
colight_prose/block_cache.py
colight_prose/block_graph.py
colight_prose/client_registry.py
colight_prose/constants.py
colight_prose/dependency_analyzer.py
colight_prose/executor.py
colight_prose/file_graph.py
colight_prose/file_resolver.py
colight_prose/incremental_executor.py
colight_prose/json_api.py
colight_prose/model.py
colight_prose/module_resolver.py
colight_prose/parser.py
colight_prose/pep723.py
colight_prose/pragma.py
colight_prose/server.py
colight_prose/utils.py
colight_prose/static/__init__.py
colight_prose/static/build_helper.py
colight_prose/static/builder.py
colight_prose/static/generator.py
colight_prose/static/server_watch.py
colight_prose/static/watcher.py
colight_prose-2025.7.8.dist-info/METADATA
colight_prose-2025.7.8.dist-info/WHEEL
colight_prose-2025.7.8.dist-info/entry_points.txt
colight_prose-2025.7.8.dist-info/RECORD
