Metadata-Version: 2.4
Name: colight-prose
Version: 2025.7.8
Summary: Static site generator for Colight visualizations
Author-email: Matthew Huebert <me@matt.is>
License: MIT
Requires-Python: >=3.10
Requires-Dist: click>=8.1
Requires-Dist: colight
Requires-Dist: libcst>=1.4
Requires-Dist: markdown>=3.5
Requires-Dist: watchfiles>=0.21.0
Requires-Dist: websockets>=12.0
Requires-Dist: werkzeug>=3.1.3
